{"stat.flyOneCm":27453,"stat.pickup.minecraft.glass_bottle":37,"stat.walkOneCm":17863,"stat.pickup.minecraft.wheat_seeds":1,"stat.pickup.immersiveengineering.seed":1,"stat.jump":227,"stat.mineBlock.minecraft.leaves":5,"stat.playOneMinute":11718,"stat.fallOneCm":1103,"stat.climbOneCm":991,"stat.sneakTime":168,"stat.damageDealt":2220,"stat.crouchOneCm":382,"stat.timeSinceDeath":11718,"stat.pickup.minecraft.dirt":6,"stat.useItem.minecraft.dirt":5,"stat.sprintOneCm":9402,"stat.mineBlock.minecraft.dirt":8,"stat.mobKills":11,"stat.useItem.minecraft.stone_slab2":1,"stat.useItem.minecraft.spawn_egg":19,"stat.mineBlock.biomesoplenty.plant_0":1,"stat.killEntity.furantur":11}